linguakit/__init__.py
linguakit/linguakit.py
linguakit-0.0.7a0.dist-info/LICENSE
linguakit-0.0.7a0.dist-info/METADATA
linguakit-0.0.7a0.dist-info/WHEEL
linguakit-0.0.7a0.dist-info/top_level.txt
linguakit-0.0.7a0.dist-info/RECORD
