Metadata-Version: 2.1
Name: linguakit
Version: 0.0.7a0
Summary: Python wrapper for Linguakit's Perl implementation
Home-page: https://github.com/brunneis/python-linguakit
Author: Rodrigo Martínez
Author-email: dev@brunneis.com
License: GNU General Public License v3.0
Platform: UNKNOWN
Classifier: Development Status :: 4 - Beta
Classifier: Environment :: Console
Classifier: Intended Audience :: Developers
Classifier: License :: OSI Approved :: GNU General Public License v3 (GPLv3)
Classifier: Operating System :: POSIX :: Linux
Classifier: Programming Language :: Python :: 3.6
Classifier: Programming Language :: Python :: Implementation :: PyPy
Classifier: Topic :: Software Development :: Libraries :: Python Modules
Requires-Dist: pexpect
